{
  "@context": "http://schema.org",
  "@type": [
    "BioChemEntity",
    "Sample"
  ],
  "identifier": [
    "SAMN03840244",
    "MMP03840244"
  ],
  "name": "Marinovum algicola DG 898",
  "url": "https://mmp.sfb.uit.no/databases/marref/#/records/MMP03840244",
  "description": "Algal symbiont",
  "dataset": [
    "http://www.ebi.ac.uk/ena/data/search?query=PRJNA63153",
    "https://www.arb-silva.de/search/show/ssu/insdc/63153",
    "https://www.arb-silva.de/search/show/lsu/insdc/63153",
    "http://www.ebi.ac.uk/ena/data/view/GCF_001046955.1"
  ],
  "additionalProperty": [
    {
      "@type": "PropertyValue",
      "name": "Geographic Location (GAZ)",
      "value": "Yellow Sea",
      "valueReference": [
        {
          "@type": "CategoryCode",
          "name": "Yellow Sea",
          "url": "https://www.ebi.ac.uk/ols/ontologies/gaz/terms?iri=http%3A%2F%2Fpurl.obolibrary.org%2Fobo%2FGAZ_00004690"
        }
      ]
    },
    {
      "@type": "PropertyValue",
      "name": "Organism",
      "value": "Marinovum algicola",
      "valueReference": [
        {
          "@type": "CategoryCode",
          "name": "Marinovum algicola",
          "url": "https://www.ncbi.nlm.nih.gov/Taxonomy/Browser/wwwtax.cgi?id=988812"
        }
      ]
    }
  ]
}