{
  "@context": "http://schema.org",
  "@type": [
    "BioChemEntity",
    "Sample"
  ],
  "identifier": [
    "SAMN04487764",
    "MMP04487764"
  ],
  "name": "Gillisia sp. Hel1_33_143",
  "url": "https://mmp.sfb.uit.no/databases/marref/#/records/MMP04487764",
  "description": "Gillisia sp. Hel1_33_143",
  "dataset": [
    "http://www.ebi.ac.uk/ena/data/search?query=PRJEB16403",
    "https://www.arb-silva.de/search/show/ssu/insdc/16403",
    "https://www.arb-silva.de/search/show/lsu/insdc/16403",
    "http://www.ebi.ac.uk/ena/data/view/GCA_900104765.1"
  ],
  "additionalProperty": [
    {
      "@type": "PropertyValue",
      "name": "Organism",
      "value": "Gillisia sp.",
      "valueReference": [
        {
          "@type": "CategoryCode",
          "name": "Gillisia sp.",
          "url": "https://www.ncbi.nlm.nih.gov/Taxonomy/Browser/wwwtax.cgi?id=1336796"
        }
      ]
    }
  ]
}